pygremlinbox_cddl_1_0/__init__.py
pygremlinbox_cddl_1_0-1.4.0.dist-info/licenses/LICENCE
pygremlinbox_cddl_1_0-1.4.0.dist-info/METADATA
pygremlinbox_cddl_1_0-1.4.0.dist-info/WHEEL
pygremlinbox_cddl_1_0-1.4.0.dist-info/top_level.txt
pygremlinbox_cddl_1_0-1.4.0.dist-info/RECORD
